pytsx/main.py
pyTSx-0.9.7.dist-info/LICENSE
pyTSx-0.9.7.dist-info/METADATA
pyTSx-0.9.7.dist-info/WHEEL
pyTSx-0.9.7.dist-info/entry_points.txt
pyTSx-0.9.7.dist-info/top_level.txt
pyTSx-0.9.7.dist-info/RECORD
