Metadata-Version: 2.1
Name: pyTSx
Version: 0.9.7
Summary: Time Series Analysis with Python and Spark.
Author-email: "Dr. Mirko Kämpf" <mirko.kaempf@gmail.com>
License: Copyright 2023 Dr. Mirko Kämpf
Project-URL: Homepage, https://github.com/kamir/pyTSx
Keywords: time series,complex systems,correlation,long term memory,DFA,MF-DFA
Classifier: License :: OSI Approved :: MIT License
Classifier: Programming Language :: Python
Classifier: Programming Language :: Python :: 3
Requires-Python: >=3.7
License-File: LICENSE
Requires-Dist: html2text
Requires-Dist: tomli ; python_version < "3.11"
Provides-Extra: dev
Requires-Dist: black ; extra == 'dev'
Requires-Dist: bumpver ; extra == 'dev'
Requires-Dist: isort ; extra == 'dev'
Requires-Dist: pip-tools ; extra == 'dev'
Requires-Dist: pytest ; extra == 'dev'
